rabbit_todo/__init__.py
rabbit_todo/cmd/__init__.py
rabbit_todo/cmd/cli.py
rabbit_todo/common/__init__.py
rabbit_todo/common/messages.py
rabbit_todo/common/result.py
rabbit_todo/core/__init__.py
rabbit_todo/core/i_task_repository.py
rabbit_todo/core/task.py
rabbit_todo/core/task_id_generator.py
rabbit_todo/entry_point.py
rabbit_todo/io/__init__.py
rabbit_todo/io/file_handler.py
rabbit_todo/io/io_config/__init__.py
rabbit_todo/io/io_config/json_config.py
rabbit_todo/io/io_config/path_config.py
rabbit_todo/io/json_task_repository.py
rabbit_todo-0.2.1.dist-info/entry_points.txt
rabbit_todo-0.2.1.dist-info/LICENSE
rabbit_todo-0.2.1.dist-info/METADATA
rabbit_todo-0.2.1.dist-info/WHEEL
rabbit_todo-0.2.1.dist-info/RECORD
