Metadata-Version: 2.1
Name: rabbit-todo
Version: 0.2.1
Summary: The Simple Todo Tool in CLI
Home-page: https://github.com/MayugeStudio
License: Apache-2.0
Keywords: todo,cli,simple,task-management,project-management,productivity,organizer,terminal,agenda
Author: Mayuge
Author-email: mayuge.studio.public@gmail.com
Requires-Python: >=3.9,<4.0
Classifier: Development Status :: 3 - Alpha
Classifier: Environment :: Console
Classifier: Intended Audience :: Developers
Classifier: License :: OSI Approved :: Apache Software License
Classifier: Programming Language :: Python :: 3
Classifier: Programming Language :: Python :: 3.9
Classifier: Programming Language :: Python :: 3.10
Classifier: Programming Language :: Python :: 3.11
Classifier: Programming Language :: Python :: 3.12
Classifier: Topic :: Utilities
Classifier: Typing :: Typed
Requires-Dist: click (>=8.1.7,<9.0.0)
Requires-Dist: colorama (>=0.4.6,<0.5.0)
Project-URL: Repository, https://github.com/MayugeStudio/rabbit-todo
